README
setup.py
filmweb/Movie.py
filmweb/Person.py
filmweb/__init__.py
filmweb/_exceptions.py
filmweb/addon.py
filmweb/func.py
filmweb/tests.py
filmweb/vars.py
filmweb/parser/HTMLGrabber.py
filmweb/parser/MovieParser.py
filmweb/parser/ObjectParser.py
filmweb/parser/PersonParser.py
filmweb/parser/__init__.py
filmwebpy.egg-info/PKG-INFO
filmwebpy.egg-info/SOURCES.txt
filmwebpy.egg-info/dependency_links.txt
filmwebpy.egg-info/namespace_packages.txt
filmwebpy.egg-info/not-zip-safe
filmwebpy.egg-info/requires.txt
filmwebpy.egg-info/top_level.txt