Metadata-Version: 1.0
Name: filmwebpy
Version: 0.1.1.8
Summary: Python parser for Filmweb
Home-page: http://github.com/hoffmannkrzysztof/filmwebpy
Author: Krzysztof Hoffmann
Author-email: krzysiekpl@gmail.com
License: GPL
Keywords: python filmweb parser
Platform: UNKNOWN
Classifier: Programming Language :: Python
